{"202205151406": {"Year": "22", "Mon": "5", "Day": "15", "Hr": "14", "Min": "6", "Loc": "1", "GF": "100", "Err": "0", "Qbatt": "130", "Im": "45", "UeL": "10", "Ue4": "0", "Ue3": "70", "Ue2": "99", "Ue1": "150146", "Iv": "492008", "P_Weight": "7.0", "P_Vol[l]": "4.7", "rH_i": "7.0", "Temp_i": "4.7", "TPC": "827.5", "PM1": "79.0", "PM2.5": "64.0", "PM10": "6.5", "TC": "148049"}, "202205151407": {"Year": "22", "Mon": "5", "Day": "15", "Hr": "14", "Min": "7", "Loc": "1", "GF": "100", "Err": "0", "Qbatt": "130", "Im": "46", "UeL": "20", "Ue4": "0", "Ue3": "70", "Ue2": "95", "Ue1": "151143", "Iv": "495116", "P_Weight": "8.4", "P_Vol[l]": "5.4", "rH_i": "8.4", "Temp_i": "5.4", "TPC": "333.7", "PM1": "88.5", "PM2.5": "80.4", "PM10": "0.4", "TC": "145279"}, "202205151408": {"Year": "22", "Mon": "5", "Day": "15", "Hr": "14", "Min": "8", "Loc": "1", "GF": "100", "Err": "0", "Qbatt": "130", "Im": "41", "UeL": "66", "Ue4": "0", "Ue3": "75", "Ue2": "90", "Ue1": "157314", "Iv": "492403", "P_Weight": "3.3", "P_Vol[l]": "6.7", "rH_i": "3.3", "Temp_i": "6.7", "TPC": "795.0", "PM1": "31.6", "PM2.5": "81.9", "PM10": "8.0", "TC": "140487"}, "202205151409": {"Year": "22", "Mon": "5", "Day": "15", "Hr": "14", "Min": "9", "Loc": "1", "GF": "100", "Err": "0", "Qbatt": "130", "Im": "49", "UeL": "61", "Ue4": "0", "Ue3": "78", "Ue2": "90", "Ue1": "156911", "Iv": "494329", "P_Weight": "8.5", "P_Vol[l]": "3.4", "rH_i": "8.5", "Temp_i": "3.4", "TPC": "791.8", "PM1": "1.1", "PM2.5": "38.1", "PM10": "3.7", "TC": "147087"}, "202205151410": {"Year": "22", "Mon": "5", "Day": "15", "Hr": "14", "Min": "10", "Loc": "1", "GF": "100", "Err": "0", "Qbatt": "130", "Im": "43", "UeL": "57", "Ue4": "0", "Ue3": "72", "Ue2": "92", "Ue1": "155944", "Iv": "491974", "P_Weight": "8.9", "P_Vol[l]": "2.2", "rH_i": "8.9", "Temp_i": "2.2", "TPC": "960.7", "PM1": "23.6", "PM2.5": "93.1", "PM10": "5.9", "TC": "144745"}, "202205151411": {"Year": "22", "Mon": "5", "Day": "15", "Hr": "14", "Min": "11", "Loc": "1", "GF": "100", "Err": "0", "Qbatt": "130", "Im": "42", "UeL": "23", "Ue4": "0", "Ue3": "74", "Ue2": "97", "Ue1": "156022", "Iv": "494159", "P_Weight": "0.1", "P_Vol[l]": "2.0", "rH_i": "0.1", "Temp_i": "2.0", "TPC": "240.0", "PM1": "80.0", "PM2.5": "27.8", "PM10": "7.3", "TC": "145199"}, "202205151412": {"Year": "22", "Mon": "5", "Day": "15", "Hr": "14", "Min": "12", "Loc": "1", "GF": "100", "Err": "0", "Qbatt": "130", "Im": "45", "UeL": "32", "Ue4": "0", "Ue3": "77", "Ue2": "98", "Ue1": "151601", "Iv": "492487", "P_Weight": "8.0", "P_Vol[l]": "3.9", "rH_i": "8.0", "Temp_i": "3.9", "TPC": "940.9", "PM1": "15.0", "PM2.5": "7.8", "PM10": "6.2", "TC": "144871"}, "202205151413": {"Year": "22", "Mon": "5", "Day": "15", "Hr": "14", "Min": "13", "Loc": "1", "GF": "100", "Err": "0", "Qbatt": "130", "Im": "45", "UeL": "91", "Ue4": "0", "Ue3": "78", "Ue2": "93", "Ue1": "157657", "Iv": "497786", "P_Weight": "2.6", "P_Vol[l]": "1.3", "rH_i": "2.6", "Temp_i": "1.3", "TPC": "414.0", "PM1": "32.3", "PM2.5": "65.1", "PM10": "6.8", "TC": "140183"}, "202205151414": {"Year": "22", "Mon": "5", "Day": "15", "Hr": "14", "Min": "14", "Loc": "1", "GF": "100", "Err": "0", "Qbatt": "130", "Im": "42", "UeL": "43", "Ue4": "0", "Ue3": "74", "Ue2": "94", "Ue1": "150562", "Iv": "492614", "P_Weight": "7.6", "P_Vol[l]": "8.0", "rH_i": "7.6", "Temp_i": "8.0", "TPC": "974.1", "PM1": "48.0", "PM2.5": "11.8", "PM10": "5.6", "TC": "143115"}, "202205151415": {"Year": "22", "Mon": "5", "Day": "15", "Hr": "14", "Min": "15", "Loc": "1", "GF": "100", "Err": "0", "Qbatt": "130", "Im": "41", "UeL": "68", "Ue4": "0", "Ue3": "77", "Ue2": "94", "Ue1": "156859", "Iv": "494082", "P_Weight": "8.9", "P_Vol[l]": "4.5", "rH_i": "8.9", "Temp_i": "4.5", "TPC": "973.9", "PM1": "3.4", "PM2.5": "99.7", "PM10": "0.9", "TC": "149196"}, "202205151416": {"Year": "22", "Mon": "5", "Day": "15", "Hr": "14", "Min": "16", "Loc": "1", "GF": "100", "Err": "0", "Qbatt": "130", "Im": "43", "UeL": "15", "Ue4": "0", "Ue3": "74", "Ue2": "92", "Ue1": "155482", "Iv": "491503", "P_Weight": "6.0", "P_Vol[l]": "0.2", "rH_i": "6.0", "Temp_i": "0.2", "TPC": "933.7", "PM1": "21.4", "PM2.5": "64.3", "PM10": "0.6", "TC": "142411"}, "202205151417": {"Year": "22", "Mon": "5", "Day": "15", "Hr": "14", "Min": "17", "Loc": "1", "GF": "100", "Err": "0", "Qbatt": "130", "Im": "46", "UeL": "64", "Ue4": "0", "Ue3": "78", "Ue2": "98", "Ue1": "152421", "Iv": "494037", "P_Weight": "4.8", "P_Vol[l]": "7.8", "rH_i": "4.8", "Temp_i": "7.8", "TPC": "961.6", "PM1": "19.2", "PM2.5": "14.5", "PM10": "6.1", "TC": "142267"}, "202205151418": {"Year": "22", "Mon": "5", "Day": "15", "Hr": "14", "Min": "18", "Loc": "1", "GF": "100", "Err": "0", "Qbatt": "130", "Im": "45", "UeL": "95", "Ue4": "0", "Ue3": "78", "Ue2": "95", "Ue1": "156143", "Iv": "495057", "P_Weight": "6.0", "P_Vol[l]": "5.1", "rH_i": "6.0", "Temp_i": "5.1", "TPC": "344.5", "PM1": "81.0", "PM2.5": "18.2", "PM10": "4.8", "TC": "142911"}, "202205151419": {"Year": "22", "Mon": "5", "Day": "15", "Hr": "14", "Min": "19", "Loc": "1", "GF": "100", "Err": "0", "Qbatt": "130", "Im": "40", "UeL": "95", "Ue4": "0", "Ue3": "78", "Ue2": "97", "Ue1": "152976", "Iv": "490959", "P_Weight": "1.6", "P_Vol[l]": "5.7", "rH_i": "1.6", "Temp_i": "5.7", "TPC": "67.6", "PM1": "4.8", "PM2.5": "13.2", "PM10": "3.3", "TC": "147786"}}